pyhocon_dantic/__init__.py
pyhocon_dantic-0.0.4.dist-info/LICENSE
pyhocon_dantic-0.0.4.dist-info/METADATA
pyhocon_dantic-0.0.4.dist-info/WHEEL
pyhocon_dantic-0.0.4.dist-info/top_level.txt
pyhocon_dantic-0.0.4.dist-info/RECORD
